pypackinit.py
pypackinit-1.0.dist-info/LICENSE
pypackinit-1.0.dist-info/METADATA
pypackinit-1.0.dist-info/WHEEL
pypackinit-1.0.dist-info/entry_points.txt
pypackinit-1.0.dist-info/top_level.txt
pypackinit-1.0.dist-info/RECORD
