Metadata-Version: 2.1
Name: pypackinit
Version: 1.0
Summary: Rapid python package skeleton generator
Home-page: https://github.com/massarom/pypackinit
Author: Marcello Massaro
Author-email: 18736562+massarom@users.noreply.github.com
License: MIT License
Keywords: setuptools,packaging
Platform: UNKNOWN
Classifier: Development Status :: 4 - Beta
Classifier: License :: OSI Approved :: MIT License
Classifier: Programming Language :: Python :: 3
Classifier: Topic :: Software Development :: Code Generators
Classifier: Topic :: System :: Software Distribution
